{
  "project_info": {
    "project_number": "640196927691",
    "project_id": "roomrentinggroup1",
    "storage_bucket": "roomrentinggroup1.firebasestorage.app"
  },
  "client": [
    {
      "client_info": {
        "mobilesdk_app_id": "1:640196927691:android:30f59da6b1505482ea7b4e",
        "android_client_info": {
          "package_name": "com.example.room_renting_group1"
        }
      },
      "oauth_client": [],
      "api_key": [
        {
          "current_key": "AIzaSyDbK-GoIyA9dlXJbSFbBxcmod5NK6DncTo"
        }
      ],
      "services": {
        "appinvite_service": {
          "other_platform_oauth_client": []
        }
      }
    }
  ],
  "configuration_version": "1"
}